{"is_source_file": true, "format": "Python", "description": "WSGI configuration file for deploying a Django application, setting up the WSGI application callable and environment variables.", "external_files": ["django.core.wsgi", "config.settings"], "external_methods": ["django.core.wsgi.get_wsgi_application"], "published": ["application"], "classes": [], "methods": [{"name": "get_wsgi_application", "description": "Function imported from django.core.wsgi that creates the WSGI application callable."}], "calls": ["django.core.wsgi.get_wsgi_application"], "search-terms": ["WSGI", "Django deployment", "application callable", "WSGI config"], "state": 2, "file_id": 17, "knowledge_revision": 34, "git_revision": "1604c1a5933669f5998d52c91c7f9058fd270b7d", "ctags": [{"_type": "tag", "name": "application", "path": "/home/kavia/workspace/code-generation/event-management-api-7e972b0f/event_management_backend/config/wsgi.py", "pattern": "/^application = get_wsgi_application()$/", "language": "Python", "kind": "variable"}], "hash": "412e3606d946f0fb4dbc98443c4cf8bb", "format-version": 4, "code-base-name": "event_management_backend", "filename": "event_management_backend/config/wsgi.py", "fields": [{"name": "application = get_wsgi_application()", "scope": "", "scopeKind": "", "description": "unavailable"}], "revision_history": [{"34": "1604c1a5933669f5998d52c91c7f9058fd270b7d"}]}